godot_pypi_test-0.0.4.dist-info/licenses/LICENSE
test_pypi/__init__.py
test_pypi/core.py
godot_pypi_test-0.0.4.dist-info/METADATA
godot_pypi_test-0.0.4.dist-info/WHEEL
godot_pypi_test-0.0.4.dist-info/top_level.txt
godot_pypi_test-0.0.4.dist-info/RECORD
