Metadata-Version: 2.4
Name: godot-pypi-test
Version: 0.0.4
Summary: 一句话描述
Author-email: hyooeewee <hughie-ngai@outlook.com>
Classifier: Programming Language :: Python :: 3
Classifier: License :: OSI Approved :: MIT License
Classifier: Operating System :: OS Independent
Requires-Python: >=3.8
License-File: LICENSE
Requires-Dist: build>=1.2.2.post1
Requires-Dist: python-dotenv>=1.0.1
Requires-Dist: twine>=6.1.0
Dynamic: license-file
